[
  {
    "id": "tomoshika",
    "name": "緋笠 トモシカ",
    "reading": "Hikasa Tomoshika",
    "unit": "VOMS",
    "icon": "fa-solid fa-fire",
    "color": "#ff4d4d",
    "rgbColor": "255, 77, 77",
    "tags": ["#緋笠トモシカ", "#シカ友", "#トモシカクイズ"],
    "profile": {
      "debut": "2020年3月19日",
      "birthday": "9月21日",
      "height": "138cm",
      "age": "秘密",
      "fanName": "シカ友、雑魚",
      "fanMark": "🦌"
    },
    "bio": "ゲーム配信系のVTuberで、「炎」属性のおしゃべりモンスター。頭の炎が消えるとアイデンティティが無くなり死んでしまいます。演技力・企画力が高く、茶番を好む傾向があります。「煽り100、イキり100、企画力100、煽り耐性0」と評される芸人魂あふれるプレイスタイルが魅力。",
    "episodes": [
      {
        "title": "伝説の斜め上耐久配信：羊1万匹＆3時間瞑想",
        "desc": "羊を1万匹数える配信（約11時間43分）や、3時間目を閉じて瞑想するだけのシュールな配信など、常人には真似できない斜め上の耐久企画を完遂する精神力を持つ。"
      },
      {
        "title": "愛すべきポンコツ・茶番での大事故",
        "desc": "エイプリルフールに凝った茶番動画を用意するも、本番でマイクをミュートにしたまま無音で進行してしまい、配信後に猛省会を開くという「大事故」を等身大の魅力として昇華させた。"
      },
      {
        "title": "人生最大の誇りは「マイクラ肝試し」1位",
        "desc": "『マイクラ肝試し』で1位を取ったことを異常なほど誇りにしており、お葬式の遺言でもこの実績を読み上げてほしいと語るほど、勝負事（特に肝試し）への情熱は熱い。"
      },
      {
        "title": "将棋VTuberへの覚醒と「初狩り」の優しさ",
        "desc": "2025年から将棋に猛烈にハマり、「初狩りしてやる」とイキりながらも、実際には初心者に手取り足取り教え、相手がハマると大喜びする面倒見の良さが漏れ出ている。"
      }
    ]
  },
  {
    "id": "miuneru",
    "name": "羽渦 ミウネル",
    "reading": "Haneuzu Miuneru",
    "unit": "VOMS",
    "icon": "fa-solid fa-tornado",
    "color": "#70d6ff",
    "rgbColor": "112, 214, 255",
    "tags": ["#羽渦ミウネル", "#うずまき", "#ミウネルさんはそんなこと言わない"],
    "profile": {
      "debut": "2021年10月3日",
      "birthday": "9月11日",
      "height": "133cm",
      "age": "成人はしている（お酒・運転可）",
      "fanName": "うずまき",
      "fanMark": "🌀"
    },
    "bio": "“渦”属性のおしゃべりモンスター。透明感のある美しい声としっかり者な性格で、VOMSの「清楚担当」として知られている。非常に熱心な努力家であり、謎解きやストーリー重視のゲームをじっくり全回収するプレイスタイルを好む。",
    "episodes": [
      {
        "title": "応募フォーム9000字＆パワポプレゼン事件",
        "desc": "VOMSのオーディション応募時に志望動機を9000字も書き連ね、さらに面談ではPowerPointによるプレゼン資料を持参して熱烈にアピールした、VOMS愛が重すぎる伝説を持つ。"
      },
      {
        "title": "清楚ボイスから放たれる「#ミウネルさんはそんなこと言わない」",
        "desc": "『マリオサンシャイン』配信中、敵に対して「今日はげその唐揚げだー！」等と物騒な発言を連発。GYARI氏により専用タグを作られ公式切り抜きまで制作されるギャップが魅力。"
      },
      {
        "title": "「8000万ドルの悲鳴」",
        "desc": "極度のホラー苦手だが、その悲鳴の美しさは「8000万ドルの悲鳴」と称賛される。あまりの絶叫に回線が落ちるというハプニングを引き起こすほどの迫力を持つ。"
      },
      {
        "title": "ポケモン愛と、容赦ない「忘れろビーム」",
        "desc": "自分のポケモンをNPCのものと勘違いしてしまった際、証拠隠滅のために「忘れろビーム！」を放ってしれっと元に戻そうとするなど、時折見せるお茶目な言動が愛されている。"
      }
    ]
  },
  {
    "id": "ryugon",
    "name": "大門地 リューゴン",
    "reading": "Daimonji Ryugon",
    "unit": "VOMS",
    "icon": "fa-solid fa-dragon",
    "color": "#a67c52",
    "rgbColor": "166, 124, 82",
    "tags": ["#DaimonjiRyugon", "#龍星軍", "#RyugOnAir"],
    "profile": {
      "debut": "2021年10月3日",
      "birthday": "3月14日",
      "height": "150cm",
      "bloodType": "AB型",
      "fanName": "龍星軍",
      "attribute": "地龍"
    },
    "bio": "VOMS初の男性VTuberで、“地龍”属性のおしゃべりモンスター。元自衛官という異色の経歴を持ち、体力と筋肉で解決する脳筋プレイスタイル。決して無言にならない「脊髄反射トーク」で、長時間の耐久配信も難なくこなすタフさが武器。",
    "episodes": [
      {
        "title": "48時間連続ARK！仕事を辞めて配信に捧げる",
        "desc": "『ARK』に心酔し、48時間連続配信を宣言。収益化も通っていない時期に「ARKのために仕事を辞めた」という、人生を賭けたレベルのハマりっぷりを見せる長時間配信モンスター。"
      },
      {
        "title": "元自衛官ならではのトラウマと退職理由",
        "desc": "起床ラッパが未だにトラウマであることや、上官とのバーベキューという体育会系のノリが合わずに辞めたことなど、自衛隊時代の経験を赤裸々かつユーモラスに語る。"
      },
      {
        "title": "親友「Vオタの佐藤」との絆と奴隷契約",
        "desc": "一番の仲良しであるリア友「佐藤」が切り抜きや英訳を担当。受かったら字幕をつけるという約束を逆手に取り、奴隷（？）のように働かせているという微笑ましい（？）関係。",
        "order": 1
      },
      {
        "title": "虫も食う！NGなしの体当たり精神",
        "desc": "寝坊のケジメとして「カブトムシ」を実食したり、将来的な昆虫食を同僚に勧めたりと、謎のバイタリティとNGなしの根性でファンを驚かせ続けている。"
      }
    ]
  },
  {
    "id": "sanparo",
    "name": "善額 サンパロー",
    "reading": "Zengaku Sanparo",
    "unit": "VOMS",
    "icon": "fa-solid fa-sun",
    "color": "#ffcc00",
    "rgbColor": "255, 204, 0",
    "tags": ["#善額サンパロー", "#おとなりサン", "#太曜ロードショー"],
    "profile": {
      "debut": "2023年11月19日",
      "birthday": "6月3日",
      "height": "152cm",
      "bloodType": "B型",
      "fanName": "おとなりサン",
      "fanMark": "🌞"
    },
    "bio": "“太陽”属性のおしゃべりモンスター。明るく陽気なお兄ちゃん的存在。1900時間を超えるスプラトゥーンの腕前を持つガチゲーマーでありつつ、私生活では独り言を自動ドアに聞かせるお茶目な一面も。圧倒的なトーク力で場を盛り上げるムードメーカー。",
    "episodes": [
      {
        "title": "「岩盤発破」への異常な執着",
        "desc": "『エルデンリング』で初期ステータスのまま魔術「岩盤発破」のみでボスに挑み、「走って葉っぱで破壊しろ！」と叫び続ける独自の縛りプレイでリスナーを熱狂させた。"
      },
      {
        "title": "ガチグラ「よろず屋サンちゃん」のエモい結末",
        "desc": "ストグラ系企画では自転車で駆け巡るよろず屋として活動。最終日には「乙女の涙が一番盗みたいもの」というキザな台詞を残し、普段のキャラとは違うエモいドラマで感動を呼んだ。"
      },
      {
        "title": "ファンへの愛を形にする「サンキューカード」",
        "desc": "収益化記念などで、リスナー一人ひとりに向けたイラスト付き手書きサンキューカードを、長時間かけて作成する。ファンを非常に大切にする誠実な姿勢が支持されている。"
      },
      {
        "title": "オーディションでの「FF9」プレゼン事件",
        "desc": "最終面接で自己アピールそっちのけでGYARI氏と『FF9』の思い出話で1時間半も盛り上がってしまったという、生粋のゲーム好きが伺えるエピソードを持つ。"
      }
    ]
  },
  {
    "id": "noruju",
    "name": "植峰 ノルジュ",
    "reading": "Uemine Noruju",
    "unit": "VOMS",
    "icon": "fa-solid fa-leaf",
    "color": "#4caf50",
    "rgbColor": "76, 175, 80",
    "tags": ["#植峰ノルジュ", "#ノルジュが生えた", "#う絵みね"],
    "profile": {
      "debut": "2023年11月19日",
      "birthday": "12月7日",
      "height": "141cm",
      "bloodType": "O型",
      "fanName": "森茂",
      "attribute": "森"
    },
    "bio": "“森”属性のおしゃべりモンスター。頭の木が伐採されると死んでしまう宿命を持つ。クールな印象とは裏腹に、地球を爆発させるほどのポンコツっぷりや、ファンサをピーナッツと間違えられる愛されキャラ。銀魂をバイブルとする「銀魂女子」でもある。",
    "episodes": [
      {
        "title": "初配信でテンパりすぎて「地球を爆発」させる",
        "desc": "初配信の開始早々、操作ミスにより背景の地球を爆発させるという衝撃的なデビューを飾る。パニックで時間の計算も合わなくなるなど、開始数分でポンコツ王の片鱗を見せた。"
      },
      {
        "title": "渾身のファンサを「ピーナッツ」と間違えられる",
        "desc": "リスナーへ向けたハートのファンサが、どうしても「ピーナッツ」や「空洞」にしか見えないと大喜利の的に。「ピーナッツじゃねーから！ファンサだから！」という絶叫はもはや名言。"
      },
      {
        "title": "トイレに行くことを「仙豆を取りに行く」と呼ぶ",
        "desc": "お手洗いを「水を取りに行く」と誤魔化していたが、ツッコミに耐えかねて編み出したカッコいい言い回しが「仙豆を取りに行く（セズる）」。以降、配信での定番用語となった。"
      },
      {
        "title": "「銀魂」で義務教育を終えた女のDBガチ泣き体験",
        "desc": "知識が銀魂のパロディ経由しかなかったドラゴンボール。ゲーム実況を通じて初めて原作の熱いストーリーに触れ、配信中にガチ泣きするほど感動し、多くのリスナーの心を打った。"
      }
    ]
  },
  {
    "id": "batoya",
    "name": "未知又 バトヤ",
    "reading": "Michimata Batoya",
    "unit": "VOMS",
    "icon": "fa-solid fa-swords",
    "color": "#9c27b0",
    "rgbColor": "156, 39, 176",
    "tags": ["#未知又バトヤ", "#戦友", "#Batoyarts"],
    "profile": {
      "debut": "2023年11月19日",
      "birthday": "2月27日",
      "height": "144cm",
      "bloodType": "A型",
      "fanName": "戦友",
      "fanMark": "🆚"
    },
    "bio": "“戦”属性のおしゃべりモンスター。ヤンキー風の外見だが、中身は誠実で真面目な努力家。RPGやRTAにストイックに取り組むゲーマーとしての顔と、作詞・作曲・Mixまでこなす音楽クリエイターとしての才能を併せ持つ。",
    "episodes": [
      {
        "title": "度肝を抜いた初配信とポケモン150問連続正解",
        "desc": "自作のポケモン風画面での自己紹介や、脅威のスピードでのポケモン鳴き声クイズ150問連続正解など、圧倒的なクオリティと知識量で伝説的なデビューを飾った。"
      },
      {
        "title": "作詞・作曲・Mixすべてをこなす変拍子オタク",
        "desc": "1stシングル『Take My Go Sound!!!』や1stアルバムを自ら制作。変拍子を愛する「変拍子のオタク」として、音楽面でも唯一無二のクリエイティビティを発揮している。"
      },
      {
        "title": "ガチすぎるRTA走者としての情熱",
        "desc": "『キングダムハーツ2』のRTAイベント出場や、誕生日前日のポケモン赤全クリRTAなど、自分を追い込むストイックなプレイスタイルで多くの戦友を惹きつけている。"
      },
      {
        "title": "日本語の些細な疑問で12万いいねの大バズり",
        "desc": "「『可愛い』は『可愛よさそう』と言うのに…」という促音便に関する素朴な疑問をポストしたところ、12万いいねを超える大バズりを記録。意外なところでのバズり運も持っている。"
      }
    ]
  },
  {
    "id": "pikamee",
    "name": "天野 ピカミィ",
    "reading": "Amano Pikamee",
    "unit": "VOMS (ALUMNI)",
    "icon": "fa-solid fa-bolt",
    "color": "#ffd500",
    "rgbColor": "255, 213, 0",
    "tags": ["#Pikamee", "#天野ピカミィ", "#ケトル笑い"],
    "profile": {
      "debut": "2020年3月19日",
      "graduation": "2023年3月31日",
      "birthday": "7月13日",
      "height": "135cm",
      "fanName": "PIKARMY",
      "fanMark": "⚡"
    },
    "bio": "“雷”属性のおしゃべりモンスター。日英バイリンガルで、高音の「ケトル笑い」が世界中で愛された。IQ5兆を自称するが漢字と算数が苦手なポンコツな一面や、ゲームへの豊かな感受性、そしてドーナツへの深い愛が魅力。2023年に惜しまれつつ卒業した伝説のモンスター。",
    "episodes": [
      {
        "title": "日英ペラペラのハイテンション・バイリンガル！",
        "desc": "日本語と英語を自在に操り、世界中のファンを繋いだ。彼女の配信を通じてファン同士が互いの言語を使い始める「ピカミーム」現象を巻き起こした影響力は計り知れない。"
      },
      {
        "title": "伝説のヤカン引き笑い「ケトル笑い」",
        "desc": "笑った後の高音が、お湯の沸いたヤカンの音にそっくりなことから命名。一度聴いたら忘れられないその笑い声は、多くのリスナーに元気と笑顔を届けた彼女のトレードマーク。"
      },
      {
        "title": "家も消火器も爆発！カオスなクッキング配信",
        "desc": "料理ゲームで消火器の粉をぶちまけ、火事を起こしてもビール樽を持って逃走。最後には家（家賃5兆円）を爆破して締めるという、エンターテイナーとしての爆発力を見せつけた。"
      },
      {
        "title": "敵にも寄り添う優しさと「鬼畜ミィ」の二面性",
        "desc": "ゾンビの体調を心配するほどの優しさを持つ反面、ゲームが上手くいかないと理不尽にキレる「鬼畜ミィ」や、あつ森での「ゲスの極ミィ」など、人間味あふれる多彩な表情が愛された。"
      }
    ]
  },
  {
    "id": "monoe",
    "name": "磁富 モノエ",
    "reading": "Jitomi Monoe",
    "unit": "VOMS (ALUMNI)",
    "icon": "fa-solid fa-magnet",
    "color": "#607d8b",
    "rgbColor": "96, 125, 139",
    "tags": ["#磁富モノエ", "#ジト民", "#心地いい騒音"],
    "profile": {
      "debut": "2020年3月19日",
      "graduation": "2021年2月19日",
      "birthday": "5月12日",
      "height": "132cm",
      "bloodType": "B型",
      "fanName": "ジト民",
      "fanMark": "🧲"
    },
    "bio": "“磁”属性のおしゃべりモンスター。魅力的な低音ボイスと、まったりとしたトークがリスナーから「心地いい騒音」と評された。TRPGでの圧倒的な存在感や、まったりした雰囲気の中に潜む「イキリ陰キャ」や「サイコパス」な一面がスパイスとなった個性派モンスター。",
    "episodes": [
      {
        "title": "緊張とサイコパスが同居した伝説の初配信",
        "desc": "極度の緊張で震えながらも、履歴書に「うるせ〜〜！！」と書き込み、人間を溶かす機械を「ベリーキュート」と称するなど、初日から大物の片鱗を見せつけた。"
      },
      {
        "title": "雪山人狼で露呈した「イキリ陰キャ」伝説",
        "desc": "人狼役に当たって「さぁ、行こう。」とカッコよく決めるも、幽霊となったピカミィやトモシカに現場を抑えられ、後に「イキリ陰キャ」として盛大にいじられるという完璧なオチをつけた。"
      },
      {
        "title": "TRPGで見せた圧倒的なプレイングと世界観",
        "desc": "『シン狂気山脈V3』などのTRPG企画で活躍。でびでび・でびる氏からも絶賛される世界観構築力と、物語に命を吹き込む卓越した名演技で、多くの名シーンを生み出した。"
      },
      {
        "title": "執念の壺耐久と10万人達成の快挙",
        "desc": "チャンネル登録者10万人達成を祝うために『壺おじ』耐久を実施。見事達成した後も「関係なく壺をする」と24時間以上配信を続けクリアまで漕ぎ着けるという、凄まじい執念と根性を見せた。"
      }
    ]
  }
]
